topsis/__init__.py
topsis/topsis.py
Topsis_Vikas_102067010-1.0.8.dist-info/LICENSE.txt
Topsis_Vikas_102067010-1.0.8.dist-info/METADATA
Topsis_Vikas_102067010-1.0.8.dist-info/WHEEL
Topsis_Vikas_102067010-1.0.8.dist-info/entry_points.txt
Topsis_Vikas_102067010-1.0.8.dist-info/top_level.txt
Topsis_Vikas_102067010-1.0.8.dist-info/RECORD
