Metadata-Version: 2.1
Name: Topsis-Vikas-102067010
Version: 1.0.8
Summary: Calculates Topsis Score and Rank them accordingly
Home-page: UNKNOWN
Author: Vikas Singh
Author-email: vs8422135@gmail.com
License: MIT
Keywords: TOPSIS
Platform: UNKNOWN
Classifier: Programming Language :: Python :: 3
Classifier: License :: OSI Approved :: MIT License
Classifier: Operating System :: OS Independent
License-File: LICENSE.txt
Requires-Dist: pandas
